flowhigh/__init__.py
flowhigh/auth/__init__.py
flowhigh/auth/authentication.py
flowhigh/extraction/__init__.py
flowhigh/extraction/extractor.py
flowhigh/format/__init__.py
flowhigh/format/formatting.py
flowhigh/model/__init__.py
flowhigh/model/Agg.py
flowhigh/model/AggType.py
flowhigh/model/AlterTableStatement.py
flowhigh/model/AntiPattern.py
flowhigh/model/AntiPatterns.py
flowhigh/model/AP_Types.py
flowhigh/model/Array.py
flowhigh/model/Asterisk.py
flowhigh/model/Attr.py
flowhigh/model/BaseExpr.py
flowhigh/model/BaseExprCollectionHolder.py
flowhigh/model/BaseExprHolder.py
flowhigh/model/BetweenType.py
flowhigh/model/Case.py
flowhigh/model/Cast.py
flowhigh/model/ColumnDef.py
flowhigh/model/Const.py
flowhigh/model/CoordinateBlock.py
flowhigh/model/Copy.py
flowhigh/model/CopyStatement.py
flowhigh/model/Create.py
flowhigh/model/CreateStage.py
flowhigh/model/CreateStageStatement.py
flowhigh/model/CreateTableStatement.py
flowhigh/model/CreateView.py
flowhigh/model/CreateViewStatement.py
flowhigh/model/Current.py
flowhigh/model/DbExt.py
flowhigh/model/DBO.py
flowhigh/model/DBOHier.py
flowhigh/model/DBOSubType.py
flowhigh/model/DBOType.py
flowhigh/model/DefinedAsType.py
flowhigh/model/Delete.py
flowhigh/model/DeleteStatement.py
flowhigh/model/Direction.py
flowhigh/model/Ds.py
flowhigh/model/DsAction.py
flowhigh/model/DsSubType.py
flowhigh/model/DsType.py
flowhigh/model/Edge.py
flowhigh/model/Else.py
flowhigh/model/Error.py
flowhigh/model/Expr.py
flowhigh/model/ExprCollectionHolder.py
flowhigh/model/ExprExprCollectionHolder.py
flowhigh/model/ExprExprHolder.py
flowhigh/model/ExprHolder.py
flowhigh/model/Filter.py
flowhigh/model/FilterType.py
flowhigh/model/Frame.py
flowhigh/model/Func.py
flowhigh/model/FuncSubType.py
flowhigh/model/FuncType.py
flowhigh/model/Hashable.py
flowhigh/model/HashIgnore.py
flowhigh/model/In.py
flowhigh/model/InlineTable.py
flowhigh/model/Insert.py
flowhigh/model/InsertStatement.py
flowhigh/model/Join.py
flowhigh/model/JoinSubType.py
flowhigh-1.0.11.dist-info/entry_points.txt
flowhigh-1.0.11.dist-info/WHEEL
flowhigh-1.0.11.dist-info/METADATA
flowhigh-1.0.11.dist-info/RECORD
