Metadata-Version: 2.1
Name: flowhigh
Version: 1.0.11
Summary: Python SDK for FlowHigh
License: Proprietary
Keywords: SQLAnalyzer SDK Python
Author-email: sonra <support@sonra.io>
Requires-Python: >=3.6
Classifier: Development Status :: 3 - Alpha
Classifier: Intended Audience :: Developers
Classifier: Natural Language :: English
Classifier: Programming Language :: Python :: 3
Classifier: Programming Language :: Python :: 3.6
Classifier: Programming Language :: Python :: 3.7
Classifier: Programming Language :: Python :: 3.8
Classifier: Programming Language :: Python :: 3.9
Requires-Dist: requests>=2.14.0
Project-URL: Changelog, https://docs.sonra.io/flowhigh/master/docs/release
Project-URL: Documentation, https://docs.sonra.io/flowhigh
Project-URL: Homepage, https://flowhigh.io/
Project-URL: Repository, https://flowhigh.io/
